currency_iso4217/__init__.py
currency_iso4217/currency.json
currency_iso4217/functions.py
currency_iso4217/test.py
currency_iso4217-0.12.0.dist-info/DESCRIPTION.rst
currency_iso4217-0.12.0.dist-info/METADATA
currency_iso4217-0.12.0.dist-info/RECORD
currency_iso4217-0.12.0.dist-info/WHEEL
currency_iso4217-0.12.0.dist-info/metadata.json
currency_iso4217-0.12.0.dist-info/top_level.txt
