Metadata-Version: 2.0
Name: currency-iso4217
Version: 0.12.0
Summary: Librería para buscar divisas conforme listado ISO 4217. Last update: 2022-03-29
Home-page: https://gitlab.com/marceloiacobucci
Author: Marcelo Daniel Iacobucci
Author-email: marceloiacobucci@gmail.com
License: MIT
Platform: UNKNOWN
Classifier: Programming Language :: Python :: 3
Classifier: License :: OSI Approved :: MIT License
Classifier: Operating System :: OS Independent
